acac/__init__.py
acac/__main__.py
acac/algo_method.py
acac/atcoder.py
acac/cli.py
acac/config.py
acac/core.py
acac/create.py
acac/default_acac.toml
acac/judge.py
acac/share.py
acac/util.py
acac-0.5.0.dist-info/LICENSE
acac-0.5.0.dist-info/METADATA
acac-0.5.0.dist-info/WHEEL
acac-0.5.0.dist-info/entry_points.txt
acac-0.5.0.dist-info/RECORD
