Metadata-Version: 2.3
Name: acac
Version: 0.5.0
Summary: 競プロ便利 CLI ツール。AtCoder と アルゴ式 に対応。
License: MIT
Author: seijinrosen
Author-email: 86702775+seijinrosen@users.noreply.github.com
Requires-Python: >=3.9,<4.0
Classifier: License :: OSI Approved :: MIT License
Classifier: Programming Language :: Python :: 3
Classifier: Programming Language :: Python :: 3.9
Classifier: Programming Language :: Python :: 3.10
Classifier: Programming Language :: Python :: 3.11
Classifier: Programming Language :: Python :: 3.12
Classifier: Programming Language :: Python :: 3.13
Requires-Dist: beautifulsoup4 (>=4.11.1,<5.0.0)
Requires-Dist: lxml (>=4.9.1,<6.0.0)
Requires-Dist: pydantic (>=1.10.1,<3.0.0)
Requires-Dist: pyperclip (>=1.8.2,<2.0.0)
Requires-Dist: readchar (>=4.0.3,<5.0.0)
Requires-Dist: requests (>=2.28.1,<3.0.0)
Requires-Dist: rich (>=12.5.1,<14.0.0)
Requires-Dist: tomli (>=2.0.1,<3.0.0)
Requires-Dist: tomli-w (>=1.0.0,<2.0.0)
Requires-Dist: typing-extensions (>=4.3.0,<5.0.0)
Project-URL: Documentation, https://github.com/seijinrosen/acac
Project-URL: Homepage, https://github.com/seijinrosen
Project-URL: Repository, https://github.com/seijinrosen/acac
